messenger/Client_RW.py
messenger/JIM.py
messenger/Server.py
messenger/__init__.py
messenger/client_gui.py
messenger/common_def.py
messenger/db.py
messenger/decorators_all.py
messenger/security.py
messenger/server_gui.py
at_messenger.2021-8.2.dist-info/METADATA
at_messenger.2021-8.2.dist-info/WHEEL
at_messenger.2021-8.2.dist-info/entry_points.txt
at_messenger.2021-8.2.dist-info/top_level.txt
at_messenger.2021-8.2.dist-info/RECORD
