Metadata-Version: 2.1
Name: at-messenger.2021
Version: 8.2
Summary: A base for simple messenger with GUI
Home-page: UNKNOWN
Author: AT_Geek
Author-email: AT_Geek@mail.ru
License: GNI General Public License v3.0
Platform: UNKNOWN
Requires-Dist: PyQt5 (>=5.15)
Requires-Dist: SQLAlchemy (>=1.4.26)
